{
  "team": "Ghana",
  "youtube": [
    {
      "text": "7 - 10 min highlights from FIFA, who&#39;s with me",
      "likes": 362,
      "published": "2026-06-25T04:17:17Z"
    },
    {
      "text": "Hats off to Ghana ( particularly keeper) for defending the barrage of attacks so well for full 90 minutes.",
      "likes": 95,
      "published": "2026-06-24T22:56:01Z"
    },
    {
      "text": "Congratulations to Ghana for this honor for Africa after Ivory Coast!",
      "likes": 139,
      "published": "2026-06-24T22:18:13Z"
    },
    {
      "text": "Ghana is impressive. They couldn&#39;t even qualify to the last Africa Cup of Nations, and now they&#39;re close to reach the World Cup last 32. Cabo Verde too.",
      "likes": 41,
      "published": "2026-06-25T10:03:08Z"
    },
    {
      "text": "Well done the VAR team, they saved Englands bacon by going for that well deserved coffee at a critical moment !",
      "likes": 41,
      "published": "2026-06-25T05:54:25Z"
    },
    {
      "text": "Bellingham was right when he told the BBC he didn&#39;t deserve the man of the match award and  It probably should&#39;ve gone to one of their lads who defended so well.",
      "likes": 24,
      "published": "2026-06-24T22:53:22Z"
    },
    {
      "text": "Why didn&#39;t you guys give Ghana a penalty? Why was Bellingham allowed to cover his mouth but the Paraguayan wasn&#39;t? How did the Ghanaian player foul the English goalkeeper that rushed toward him?",
      "likes": 283,
      "published": "2026-06-24T23:40:22Z"
    },
    {
      "text": "Jude Bellingham Said AT Full Time That HE Didn&#39;t Deserve TO WIN The Player OF The Match Award",
      "likes": 72,
      "published": "2026-06-24T22:17:08Z"
    },
    {
      "text": "ghana defense is crazy",
      "likes": 17,
      "published": "2026-06-25T03:20:39Z"
    },
    {
      "text": "This is how you park the proverbial bus!",
      "likes": 27,
      "published": "2026-06-24T23:29:18Z"
    },
    {
      "text": "\ud83d\ude2eThat was penalty not given to Ghana. It was lost game for Eng. Sorry they are not winning football wc this year if they cant beat Ghana even with refree. Argentina will show you levels.",
      "likes": 24,
      "published": "2026-06-25T03:00:52Z"
    },
    {
      "text": "Their a legend in Africa that says these guys are African football heros",
      "likes": 8,
      "published": "2026-06-24T22:51:29Z"
    },
    {
      "text": "Hats off to Ghana. England may think they\u2019re winning the World Cup, but they can\u2019t even beat Ghana. It\u2019s not coming home. \ud83d\ude02\ud83d\ude02 19 shots, but no goals that is so crazy",
      "likes": 88,
      "published": "2026-06-25T00:58:15Z"
    },
    {
      "text": "Well done ghana\ud83c\udf89",
      "likes": 11,
      "published": "2026-06-24T22:17:19Z"
    },
    {
      "text": "<a href=\"https://www.youtube.com/watch?v=Qe-fptt6wXs&amp;t=80\">1:20</a> how is that not a penalty? the defender literally threw himself on the attacking player and took him down, without playing the ball",
      "likes": 24,
      "published": "2026-06-25T07:33:39Z"
    },
    {
      "text": "ghana&#39;s defence is insane bruh",
      "likes": 2,
      "published": "2026-06-25T11:22:14Z"
    },
    {
      "text": "Well done Ghana. From Papua New Guinea. Shout out to my bros Kwabina and Nana Owusu Sarfo.",
      "likes": 1,
      "published": "2026-06-25T21:50:00Z"
    },
    {
      "text": "Longer highlights please FIFA",
      "likes": 1,
      "published": "2026-06-25T13:47:29Z"
    },
    {
      "text": "the players look stiff before the game not relaxed and tense and thay carry this mental state of mind onto the pitch for the love of football SMILE  \ud83d\ude0b",
      "likes": 0,
      "published": "2026-06-26T11:07:09Z"
    },
    {
      "text": "Ghana Fufu Magic",
      "likes": 7,
      "published": "2026-06-25T02:35:30Z"
    },
    {
      "text": "Tuchel isn&#39;t getting the line up right. Why is Gordon starting the game?",
      "likes": 6,
      "published": "2026-06-25T07:07:21Z"
    },
    {
      "text": "Ghana defence \u2764",
      "likes": 5,
      "published": "2026-06-25T04:45:58Z"
    },
    {
      "text": "Ghana played very well \ud83d\udc40",
      "likes": 2,
      "published": "2026-06-25T01:17:21Z"
    },
    {
      "text": "It was the Great wall of Ghana",
      "likes": 3,
      "published": "2026-06-25T16:03:13Z"
    },
    {
      "text": "Ghana proved their strength",
      "likes": 27,
      "published": "2026-06-25T02:26:09Z"
    },
    {
      "text": "It&#39;s not coming home?",
      "likes": 1,
      "published": "2026-06-25T01:11:52Z"
    },
    {
      "text": "GOOOOOAAALLL GHANA IS GO TO WIN.",
      "likes": 1,
      "published": "2026-06-25T21:39:24Z"
    },
    {
      "text": "You must give the minutes of the positions.",
      "likes": 0,
      "published": "2026-06-25T08:59:08Z"
    },
    {
      "text": "That&#39;s what you call a defensive masterclass.",
      "likes": 0,
      "published": "2026-06-25T19:49:55Z"
    },
    {
      "text": "Japan vs Tunisia??\ud83d\ude0a",
      "likes": 0,
      "published": "2026-06-24T23:08:15Z"
    },
    {
      "text": "longer highlight than the 5 goal games btw",
      "likes": 0,
      "published": "2026-06-25T02:16:47Z"
    },
    {
      "text": "Where is the penalty?",
      "likes": 107,
      "published": "2026-06-24T22:30:07Z"
    },
    {
      "text": "Finally a well spoken commentator \ud83c\udf89\ud83c\udf89\ud83c\udf89",
      "likes": 3,
      "published": "2026-06-25T00:04:30Z"
    },
    {
      "text": "Harry maguires header is missing in those corners\ud83d\ude0f",
      "likes": 1,
      "published": "2026-06-25T06:37:53Z"
    },
    {
      "text": "Where herry kane?",
      "likes": 0,
      "published": "2026-06-25T02:56:36Z"
    },
    {
      "text": "England held scoreless at Gillette Stadium, the home stadium of the New England Patriots!",
      "likes": 10,
      "published": "2026-06-25T01:13:31Z"
    },
    {
      "text": "Well played ghana.",
      "likes": 2,
      "published": "2026-06-25T09:49:02Z"
    },
    {
      "text": "Kindly display time.",
      "likes": 0,
      "published": "2026-06-25T10:49:44Z"
    },
    {
      "text": "Pls upload 5-10second highlights",
      "likes": 0,
      "published": "2026-06-25T03:57:43Z"
    },
    {
      "text": "<a href=\"https://www.youtube.com/watch?v=Qe-fptt6wXs&amp;t=78\">1:18</a> where is penalty?<br>always against small team",
      "likes": 4,
      "published": "2026-06-25T03:15:32Z"
    },
    {
      "text": "ITS CLEAR PENALTY FOR GHANA",
      "likes": 1,
      "published": "2026-06-25T04:52:43Z"
    },
    {
      "text": "Under what pay package did the VAR and the referee get from England FA?",
      "likes": 0,
      "published": "2026-06-26T03:01:56Z"
    },
    {
      "text": "Like this, it&#39;s not coming home.",
      "likes": 0,
      "published": "2026-06-25T03:53:22Z"
    },
    {
      "text": "<a href=\"https://www.youtube.com/watch?v=Qe-fptt6wXs&amp;t=78\">1:18</a> I don&#39;t know much of rule of football, but I think this is a should be a penalty for Ghana. Love from India.",
      "likes": 0,
      "published": "2026-06-25T10:42:22Z"
    },
    {
      "text": "well done.....",
      "likes": 0,
      "published": "2026-06-25T17:29:08Z"
    },
    {
      "text": "hehehe apakah ini faktor dukun gana\ud83d\ude05 sehingga sulit di bobol.",
      "likes": 0,
      "published": "2026-06-25T02:36:51Z"
    },
    {
      "text": "My bet for the winner is either England or Brazil. Both nationals are lead by managers that have changed the spirit of the team. England is playing very well, and Brazil has become much better in defense whilst being still great in offense.",
      "likes": 0,
      "published": "2026-06-25T14:32:37Z"
    },
    {
      "text": "i from TikTok \ud83d\ude05only me?",
      "likes": 0,
      "published": "2026-06-26T03:19:27Z"
    },
    {
      "text": "I can\u2019t differentiate between england and ghana! Can you?",
      "likes": 0,
      "published": "2026-06-25T04:46:28Z"
    },
    {
      "text": "Well Done Ghana....",
      "likes": 2,
      "published": "2026-06-25T08:32:06Z"
    },
    {
      "text": "Asare with no Fear mdrr.",
      "likes": 0,
      "published": "2026-06-25T03:02:37Z"
    },
    {
      "text": "Ghana keeper\ud83c\udf89",
      "likes": 1,
      "published": "2026-06-25T17:31:26Z"
    },
    {
      "text": "Ashrof played just like in Barcelona 0 gool",
      "likes": 0,
      "published": "2026-06-25T13:53:22Z"
    },
    {
      "text": "Am I the only person who noticed Ghana played 4-4-2 in the first half and 4-4-4 in the 2nd half.",
      "likes": 0,
      "published": "2026-06-26T08:41:53Z"
    },
    {
      "text": "THATS A CLEAR RED! CLEAR PEN!",
      "likes": 11,
      "published": "2026-06-25T04:47:05Z"
    },
    {
      "text": "Ancient magic is real",
      "likes": 0,
      "published": "2026-06-25T15:56:02Z"
    },
    {
      "text": "It is probably due to the colors of their kit.",
      "likes": 0,
      "published": "2026-06-25T13:39:49Z"
    },
    {
      "text": "\u30a4\u30f3\u30b0\u30e9\u30f3\u30c9\u6226\u3060\u3051\u306f2\u5206\u3067\u3082\u9577\u304f\u611f\u3058\u308b",
      "likes": 0,
      "published": "2026-06-25T09:00:08Z"
    },
    {
      "text": "10 players in the penalty box. Thats crazy",
      "likes": 0,
      "published": "2026-06-25T05:35:36Z"
    },
    {
      "text": "No penalty for Ghana wut?????",
      "likes": 1,
      "published": "2026-06-25T07:56:02Z"
    },
    {
      "text": "Ghana Vs England+ refreree +VAR !!!!",
      "likes": 0,
      "published": "2026-06-25T06:41:55Z"
    },
    {
      "text": "Thanks to Juju Baba \ud83d\ude02",
      "likes": 1,
      "published": "2026-06-25T10:02:09Z"
    },
    {
      "text": "Ghana was robbed of a penalty",
      "likes": 5,
      "published": "2026-06-25T07:16:19Z"
    },
    {
      "text": "Ghana had more clear chances than England",
      "likes": 1,
      "published": "2026-06-25T08:15:43Z"
    },
    {
      "text": "FIFA lend me money to buy GTA 6",
      "likes": 0,
      "published": "2026-06-24T22:22:04Z"
    },
    {
      "text": "I&#39;m not supporting anyone, but if you look from a different angle, say direct back or front, it appears that the Ghana player initiated a push on the defender, perhaps that caught the referee&#39;s eye solely",
      "likes": 0,
      "published": "2026-06-25T20:20:44Z"
    },
    {
      "text": "England is just an over hyped team",
      "likes": 9,
      "published": "2026-06-25T03:33:17Z"
    },
    {
      "text": "Editor will upload 10-12 minutes highlights after  FIFA WC finish..",
      "likes": 0,
      "published": "2026-06-26T06:03:50Z"
    },
    {
      "text": "These two African teams will meet again!",
      "likes": 0,
      "published": "2026-06-25T16:57:36Z"
    },
    {
      "text": "Semenyo is the best player in the world NOW \u2764\u2764\u2764",
      "likes": 0,
      "published": "2026-06-26T09:02:35Z"
    },
    {
      "text": "Nothing wrong with England, that&#39;s their normal standard",
      "likes": 0,
      "published": "2026-06-25T07:52:22Z"
    },
    {
      "text": "in 2022 salisu challenge on Ronaldo on let to.a penalty same challenge on the Ghanaiana player there was no penalty given",
      "likes": 0,
      "published": "2026-06-25T03:31:46Z"
    },
    {
      "text": "Only highlighting England playing",
      "likes": 0,
      "published": "2026-06-25T05:59:25Z"
    },
    {
      "text": "Where is the penalty of Ghana",
      "likes": 0,
      "published": "2026-06-26T07:13:48Z"
    },
    {
      "text": "Penalty for Ghana in the end.",
      "likes": 0,
      "published": "2026-06-25T11:33:03Z"
    },
    {
      "text": "Its not coming home\ud83d\ude02\ud83d\ude02\ud83d\ude02\ud83d\ude02\ud83c\udf89\ud83c\udf89\ud83c\udf89\ud83c\udf89\ud83c\udf89\ud83c\udf89",
      "likes": 1,
      "published": "2026-06-25T09:35:50Z"
    },
    {
      "text": "It\u2019s not coming home lads \ud83d\ude14",
      "likes": 0,
      "published": "2026-06-26T13:48:10Z"
    },
    {
      "text": "Celebrating like they won&#39;t the world cup, they won&#39;t win it by a long shot",
      "likes": 0,
      "published": "2026-06-25T12:46:15Z"
    },
    {
      "text": "Harrz kane skiied it",
      "likes": 0,
      "published": "2026-06-25T18:13:40Z"
    },
    {
      "text": "Witch did his magic ....\ud83d\ude05",
      "likes": 0,
      "published": "2026-06-26T03:59:23Z"
    },
    {
      "text": "Semenyo saved England\ud83d\ude2d",
      "likes": 0,
      "published": "2026-06-25T09:08:01Z"
    },
    {
      "text": "ITS COMING HOME \ud83c\udff4\udb40\udc67\udb40\udc62\udb40\udc65\udb40\udc6e\udb40\udc67\udb40\udc7f\ud83c\udff4\udb40\udc67\udb40\udc62\udb40\udc65\udb40\udc6e\udb40\udc67\udb40\udc7f\ud83c\udff4\udb40\udc67\udb40\udc62\udb40\udc65\udb40\udc6e\udb40\udc67\udb40\udc7f",
      "likes": 0,
      "published": "2026-06-25T17:40:18Z"
    },
    {
      "text": "\u201cSometimes I got confused about who was who because they all looked so similar.\u201d\ud83d\ude0d",
      "likes": 0,
      "published": "2026-06-25T08:47:21Z"
    },
    {
      "text": "Where the aliens at?",
      "likes": 0,
      "published": "2026-06-24T23:29:00Z"
    },
    {
      "text": "I think Ghana was more on the defensive side.",
      "likes": 1,
      "published": "2026-06-24T22:53:08Z"
    },
    {
      "text": "Goalkeeper a human wall.",
      "likes": 0,
      "published": "2026-06-25T15:56:37Z"
    },
    {
      "text": "Don\u2019t like this hammering of England as usual. They did what they could against a fortified bus, on another day with better finishing, luck etc, they could have won 2 or 3 nil. They didn\u2019t lose against a team not trying to win.",
      "likes": 1,
      "published": "2026-06-25T11:25:01Z"
    },
    {
      "text": "Why flying through the air colliding with an attacker without touching the ball is not a penalty?",
      "likes": 0,
      "published": "2026-06-26T10:18:47Z"
    },
    {
      "text": "But that\u00b4s a clear penalty. It was Algeria against Argentina and now it is Ghana against England not getting the decisions.",
      "likes": 0,
      "published": "2026-06-25T23:28:55Z"
    },
    {
      "text": "Referee SAID MARTINEZ Robbed Ghana Black Stars to favour England. There was foul in the England penalty box where the goal keeper and the defender took down the Black Star player and referee Said Martinez ignored it. There was another foul where England Goalkeeper ignored the ball and completely took down the Black Star player. FIFA must level up the playing field for FAIR PLAY. Coaches must pause PLAY and call for VAR reviews right away. The world must give Referee Said Martinez RED CARD! Let&#39;s not speculate whether VAR was functioning or NOT; Referee SAID MARTINEZ must be sacked from FIFA for deliberately ignoring obvious fouls against England, a clear penalty for the Black Stars. Over 3 billion football fans in world concur that SAID Martinez should have awarded the Penalty and issue a RED to the England player who committed the foul. Why do we have Referees such as SAID MARTINEZ who don&#39;t know the basic rules of football? Ref. SAID MARTINEZ might have gotten a bribe from a prominent England fan, one will guess. As football fanatics, how do you explain such a poor officiating of this match?",
      "likes": 7,
      "published": "2026-06-25T02:07:50Z"
    },
    {
      "text": "England were lucky \ud83d\ude02",
      "likes": 0,
      "published": "2026-06-25T15:06:54Z"
    },
    {
      "text": "\u063a\u0627\u0646\u0627 \u0641\u0631\u064a\u0642 \u0631\u0627\u0626\u0639 <br>\u0634\u0643\u0631\u0627 \u0623\u0641\u0631\u064a\u0642\u064a\u0627 \u0643\u0644\u0647\u0627.. \u0623\u0628\u0637\u0627\u0644.<br>\u0645\u0635\u0631\u0649",
      "likes": 2,
      "published": "2026-06-24T22:18:15Z"
    },
    {
      "text": "Welll plaied Dear Africans \u2764",
      "likes": 0,
      "published": "2026-06-25T00:45:51Z"
    },
    {
      "text": "Black magic",
      "likes": 0,
      "published": "2026-06-25T04:37:44Z"
    },
    {
      "text": "Afria the power house of footballer proven in European country like France,",
      "likes": 0,
      "published": "2026-06-25T17:30:55Z"
    },
    {
      "text": "Don&#39;t you think its cruel to have one man pay for everything: I think it is?",
      "likes": 0,
      "published": "2026-06-25T23:30:38Z"
    },
    {
      "text": "32 Round England \ud83c\udff4\udb40\udc67\udb40\udc62\udb40\udc65\udb40\udc6e\udb40\udc67\udb40\udc7f\ud83c\udff4\udb40\udc67\udb40\udc62\udb40\udc65\udb40\udc6e\udb40\udc67\udb40\udc7f\ud83c\udff4\udb40\udc67\udb40\udc62\udb40\udc65\udb40\udc6e\udb40\udc67\udb40\udc7f",
      "likes": 0,
      "published": "2026-06-25T14:21:47Z"
    },
    {
      "text": "actually Tuchel got this match horribly wrong. I saw Spence at left back and Anthony Gordon as LW, this is disaster because England left side completely useless. I definitely would&#39;ve done things differently:-<br><br>Since Ghana plays much like Morocoo which deploy low block 5-4-1 when defending, my starting 11 goes like this - <br>a. GK - Pickford<br>b. RB - Reece James, two centre backs - Dan Burn and Konsa, LB - O&#39; Reilly<br>c. Midfield - Anderson and Mainoo as 2 CDM, Mainoo replacing Declan Rice, Morgan Rogers or Eze as number 10 replace Jude Bellingham<br>d. Front 3 - Rashford at LW, Kane as CF, Madueke at RW<br><br>U might think dropping Rice and Jude Bellingham is insane, but when really think tactically and specifically this kind of opponents this is the right thing. What I would do is the whole team: <br>1. When defending - use 4-4-2 try press high, if press high fails (first pressure line bypassed) immediately drop to mid-low block since Ghana don&#39;t have creative hub while suffocate Semenyo and Jordan Ayew at the same time. <br>2. When have the ball, England can still have the 2-3-5 attacking shape but this time is completely different because I got 2 players O&#39;Reilly and Reece James who both can do late runs and late crossing by Reece James. Basically will be even more dynamic depend on the scenario",
      "likes": 0,
      "published": "2026-06-26T06:49:02Z"
    },
    {
      "text": "Ghana v Kenya Nigeria Zimbabwe Harry Kane upfront. LoL",
      "likes": 0,
      "published": "2026-06-26T12:21:48Z"
    },
    {
      "text": "<a href=\"https://www.youtube.com/watch?v=Qe-fptt6wXs&amp;t=80\">1:20</a> P\u00eanalti claro, voadora que s\u00f3 atinge o atacante e chance clara de gol, cart\u00e3o vermelho! Arbitragem e VAR n\u00e3o est\u00e3o valendo nada!",
      "likes": 0,
      "published": "2026-06-25T22:10:03Z"
    },
    {
      "text": "\ud83c\udf89\ud83c\udf0f\ud83c\udfc6\u26bd\ufe0f\ud83c\udff4\udb40\udc67\udb40\udc62\udb40\udc65\udb40\udc6e\udb40\udc67\udb40\udc7f\ud83d\udcab\ud83c\udf40\ud83e\udd73",
      "likes": 0,
      "published": "2026-06-26T10:22:51Z"
    },
    {
      "text": "Play was Ghana against Ghana\ud83d\ude02\ud83d\ude02\ud83d\ude02\ud83d\ude02\ud83d\ude02",
      "likes": 0,
      "published": "2026-06-25T20:26:28Z"
    },
    {
      "text": "Black magic \ud83d\udc08\u200d\u2b1b",
      "likes": 0,
      "published": "2026-06-25T10:24:31Z"
    },
    {
      "text": "Clear penalty and a red card all day. Ssemenyo is one one one with the keeper to score and it run into from the back.",
      "likes": 0,
      "published": "2026-06-25T08:40:21Z"
    },
    {
      "text": "Yes, VAR blew it,  but the referee was also less than diligent.  He was trailing the play - comes into frame at <a href=\"https://www.youtube.com/watch?v=Qe-fptt6wXs&amp;t=82\">1:22</a>.  He must have at least noticed some contact and should have asked VAR to produce video.",
      "likes": 0,
      "published": "2026-06-25T22:48:09Z"
    },
    {
      "text": "It was a penalty",
      "likes": 0,
      "published": "2026-06-26T05:33:46Z"
    },
    {
      "text": "Effect juju",
      "likes": 0,
      "published": "2026-06-26T11:50:05Z"
    },
    {
      "text": "nigerians and jamaicans vs ghanans,",
      "likes": 1,
      "published": "2026-06-25T05:26:43Z"
    },
    {
      "text": "Clear Plenty to Ghana",
      "likes": 0,
      "published": "2026-06-26T05:36:33Z"
    },
    {
      "text": "For a Lazy team like England, can learn a thing or two as Ghana almost won. Almost all of them defend and attack \ud83d\ude01",
      "likes": 0,
      "published": "2026-06-25T04:12:29Z"
    },
    {
      "text": "Line Up<br><br>England \ud83c\udff4\udb40\udc67\udb40\udc62\udb40\udc65\udb40\udc6e\udb40\udc67\udb40\udc7f<br><br>Pickford 1 (GK)<br>James 24<br>Konsa 2<br>Guehi 6<br>Spence 25<br>Anderson 8<br>Rice 4<br>Madueke 20<br>Bellingham 10<br>Gordon 18<br>Kane 9 (C)<br><br>Ghana \ud83c\uddec\ud83c\udded<br><br>Asare 16 (GK)<br>Senaya 26<br>Adjetey 4<br>Opoku 18<br>Mensah 14<br>Yirenkyi 3<br>Partey 5<br>Sibo 8<br>Williams 19<br>Ayew 9 (C)<br>Semenyo 11",
      "likes": 1,
      "published": "2026-06-25T06:25:14Z"
    },
    {
      "text": "I support The Netherlands, Curacao, Japan and Ghana this world cup.",
      "likes": 2,
      "published": "2026-06-25T15:01:21Z"
    },
    {
      "text": "Penalty all day. SHAME ON ENGLAND",
      "likes": 0,
      "published": "2026-06-25T03:46:03Z"
    },
    {
      "text": "Jude Bellingham Well Deserved Player Of The Match",
      "likes": 1,
      "published": "2026-06-25T02:34:25Z"
    },
    {
      "text": "Now England  is bad both at  cricket as well as soccer \ud83d\ude02",
      "likes": 1,
      "published": "2026-06-25T03:02:30Z"
    },
    {
      "text": "England will go home earlier.",
      "likes": 0,
      "published": "2026-06-25T18:09:16Z"
    },
    {
      "text": "\u042f \u0438\u043d\u043e\u0433\u0434\u0430 \u043f\u0443\u0442\u0430\u043b\u0441\u044f \u0433\u0434\u0435 \u043a\u0442\u043e, \u0443\u0436 \u043e\u0447\u0435\u043d\u044c \u043f\u043e\u0445\u043e\u0436\u0438 \u0432\u0441\u0435...",
      "likes": 0,
      "published": "2026-06-25T00:07:23Z"
    },
    {
      "text": "Kane last shot puskas award",
      "likes": 0,
      "published": "2026-06-25T09:23:43Z"
    },
    {
      "text": "I Can&#39;t Believe Our England Team Draw Against Ghana",
      "likes": 1,
      "published": "2026-06-25T02:34:45Z"
    },
    {
      "text": "now i see the highlights it don&#39;t look like much of a penalty though",
      "likes": 0,
      "published": "2026-06-25T01:26:43Z"
    }
  ]
}