{
  "team": "Morocco",
  "articles": [
    {
      "title": "Morocco - Wikipedia summary",
      "source": "Wikipedia",
      "link": "https://en.wikipedia.org/wiki/Morocco_national_football_team",
      "published": "",
      "body": "Morocco national football team\n| This article needs additional citations for verification.  (May 2026) | \n| Nickname(s) | \u0623\u064f\u0633\u064f\u0648\u062f\u064f \u0627\u0644\u0623\u064e\u0637\u0644\u064e\u0633 (The Atlas Lions) | ||\n|---|---|---|---|\n| Association | Royal Moroccan Football Federation (FRMF) | ||\n| Confederation | CAF (Africa) | ||\n| Sub-confederation | UNAF (North Africa) | ||\n| Head coach | Mohamed Ouahbi | ||\n| Captain | Achraf Hakimi | ||\n| Most caps | Noureddine Naybet (115) | ||\n| Top scorer | Ahmed Faras (36)[1] | ||\n| Home stadium | Prince Moulay Abdellah Stadium | ||\n| FIFA code | MAR | ||\n| \n | |||\n| FIFA ranking | |||\n| Current | 7 1 (11 June 2026)[2] | ||\n| Highest | 7 (June 2026) | ||\n| Lowest | 95 (September 2010) | ||\n| First international | |||\n| Morocco 3\u20133 Iraq (Beirut, Lebanon; 19 October 1957) | |||\n| Biggest win | |||\n| Morocco 13\u20131 Saudi Arabia (Casablanca, Morocco; 6 September 1961) | |||\n| Biggest defeat | |||\n| Hungary 6\u20130 Morocco (Tokyo, Japan; 11 October 1964) | |||\n| World Cup | |||\n| Appearances | 7 (first in 1970 ) | ||\n| Best result | Fourth place (2022) | ||\n| Africa Cup of Nations | |||\n| Appearances | 20 (first in 1972 ) | ||\n| Best result | Champions (1976, 2025) | ||\n| Arab Cup | |||\n| Appearances | 5 (first in 1998 ) | ||\n| Best result | Champions (2012, 2025) | ||\n| African Nations Championship | |||\n| Appearances | 5 (first in 2014 ) | ||\n| Best result | Champions (2018, 2020, 2024) | ||\nThe Morocco national football team[a] represents Morocco in men's international football. It is controlled by the Royal Moroccan Football Federation (FRMF), the governing body for football in Morocco. It has been affiliated with FIFA since 1960, with the Confederation of African Football since 1959, and with the Union of North African Football since 2005. The team, which is known as the Atlas Lions, plays home matches at the Prince Moulay Abdellah Stadium in Rabat, and trains at the Mohammed VI Football Complex in Sal\u00e9.\nMorocco is regarded as one of Africa\u2019s most successful national football teams. They have won five continental titles, including the 1976 and 2025 editions of the African Cup of Nations. They won the African Nations Championship in 2018, 2020 and 2024. Morocco has qualified for the FIFA World Cup on seven occasions. In 1986, they made history as the first African team to win a World Cup group and advance to the knockout stage. At the 2022 World Cup, Morocco became the first African and first Arab team to reach a World Cup semi-final. They were also the third World Cup semi-finalist from outside Europe or South America. In 2025 and 2026, Morocco broke two international football world records, achieving the longest winning streak at 19 matches.\nMorocco was ranked 10th in the FIFA World Rankings in April 1998. They were Africa\u2019s highest-ranked national team for three consecutive years, from 1997 to 1999, and have occupied that position again since December 2022. As of 11 June 2026[update], Morocco is ranked 7th in the world.[3]\nMorocco is set to become the second Af"
    }
  ]
}